llama_index/storage/chat_store/redis/__init__.py
llama_index/storage/chat_store/redis/base.py
llama_index_storage_chat_store_redis-0.5.1.dist-info/METADATA
llama_index_storage_chat_store_redis-0.5.1.dist-info/WHEEL
llama_index_storage_chat_store_redis-0.5.1.dist-info/licenses/LICENSE
llama_index_storage_chat_store_redis-0.5.1.dist-info/RECORD
